fixtable/__init__.py
fixtable-0.6.dist-info/METADATA
fixtable-0.6.dist-info/WHEEL
fixtable-0.6.dist-info/entry_points.txt
fixtable-0.6.dist-info/top_level.txt
fixtable-0.6.dist-info/RECORD
