Metadata-Version: 2.1
Name: fixtable
Version: 0.6
Summary: A command-line tool to process and format Stata output tables.
Author-email: Leo Liu <auleo.liu@gmail.com>
License: MIT
Keywords: stata,table,formatting,command-line
Requires-Python: >=3.7
Requires-Dist: loguru
